plot_data/__init__.py
plot_data/colors.py
plot_data/core.py
plot_data/graph.py
plot_data/plot-data.js
plot_data/templates.py
plot_data-0.26.7.dist-info/licenses/LICENSE
plot_data-0.26.7.dist-info/METADATA
plot_data-0.26.7.dist-info/WHEEL
plot_data-0.26.7.dist-info/top_level.txt
plot_data-0.26.7.dist-info/RECORD
