Metadata-Version: 2.4
Name: plot_data
Version: 0.26.7
Summary:  A JSON based language interpreter for drawing in 2D
Home-page: https://github.com/Dessia-tech/plot_data
Author: DessiA Technologies
Author-email: root@dessia.tech
License: Creative Commons Attribution-Share Alike license
Keywords: Dataviz,drawing
Classifier: Topic :: Scientific/Engineering :: Visualization
Classifier: Development Status :: 3 - Alpha
License-File: LICENSE
Requires-Dist: matplotlib
Requires-Dist: dessia_common
Provides-Extra: test
Requires-Dist: coverage; extra == "test"
Provides-Extra: doc
Requires-Dist: sphinx; extra == "doc"
Requires-Dist: nbsphinx; extra == "doc"
Requires-Dist: pydata_sphinx_theme; extra == "doc"
Requires-Dist: nbformat; extra == "doc"
Requires-Dist: nbconvert; extra == "doc"
Requires-Dist: sphinx_copybutton; extra == "doc"
Requires-Dist: sphinx_design; extra == "doc"
Dynamic: author
Dynamic: author-email
Dynamic: classifier
Dynamic: home-page
Dynamic: keywords
Dynamic: license
Dynamic: license-file
Dynamic: provides-extra
Dynamic: requires-dist
Dynamic: summary
